ppg_common/__init__.py
ppg_common/log.yml
ppg_common/logger.py
ppg_common/clients/__init__.py
ppg_common/clients/base.py
ppg_common/clients/bind.py
ppg_common/clients/blossom.py
ppg_common/clients/bubbles.py
ppg_common/clients/buttercup.py
ppg_common/clients/copperfield.py
ppg_common/clients/pandora.py
ppg_common/config/__init__.py
ppg_common/config/cfg.py
ppg_common/errors/__init__.py
ppg_common/errors/base.py
ppg_common/errors/blossom.py
ppg_common/errors/bubbles.py
ppg_common/errors/buttercup.py
ppg_common/errors/pandora.py
ppg_common/handlers/__init__.py
ppg_common/handlers/base.py
ppg_common-1.67.dist-info/DESCRIPTION.rst
ppg_common-1.67.dist-info/METADATA
ppg_common-1.67.dist-info/RECORD
ppg_common-1.67.dist-info/WHEEL
ppg_common-1.67.dist-info/metadata.json
ppg_common-1.67.dist-info/top_level.txt
