Metadata-Version: 2.0
Name: ppg-common
Version: 1.67
Summary: Clients
Home-page: https://bitbucket.org/sbg-interns/ppg_common
Author: Sbg Core Interns
Author-email: strahinja.kovacevic994@gmail.com
License: UNKNOWN
Platform: UNKNOWN
Requires-Dist: Jinja2 (==2.9.6)
Requires-Dist: PyYAML (==3.12)
Requires-Dist: SQLAlchemy (==1.1.9)
Requires-Dist: requests (==2.13.0)
Requires-Dist: tornado (==4.5)
